beir_qdrant/__init__.py
beir_qdrant/retrieval/__init__.py
beir_qdrant/retrieval/models/__init__.py
beir_qdrant/retrieval/models/base.py
beir_qdrant/retrieval/models/colbert.py
beir_qdrant/retrieval/models/fastembed.py
beir_qdrant/retrieval/models/sentence_transformers.py
beir_qdrant/retrieval/search/__init__.py
beir_qdrant/retrieval/search/dense/__init__.py
beir_qdrant/retrieval/search/dense/dense_search.py
beir_qdrant/retrieval/search/hybrid/__init__.py
beir_qdrant/retrieval/search/hybrid/hybrid_search.py
beir_qdrant/retrieval/search/hybrid/rrf_search.py
beir_qdrant/retrieval/search/multi_vector/__init__.py
beir_qdrant/retrieval/search/multi_vector/multi_vector_reranking.py
beir_qdrant/retrieval/search/multi_vector/multi_vector_search.py
beir_qdrant/retrieval/search/multi_vector/muvera_reranking.py
beir_qdrant/retrieval/search/qdrant.py
beir_qdrant/retrieval/search/sparse/__init__.py
beir_qdrant/retrieval/search/sparse/sparse_search.py
beir_qdrant-0.5.5.dist-info/METADATA
beir_qdrant-0.5.5.dist-info/WHEEL
beir_qdrant-0.5.5.dist-info/RECORD
