Metadata-Version: 2.3
Name: beir-qdrant
Version: 0.5.5
Summary: Qdrant integration with BEIR, simplifying quality checks on standard datasets
License: Apache 2.0
Author: Kacper Łukawski
Author-email: kacper.lukawski@qdrant.com
Requires-Python: >=3.10.0,<3.14
Classifier: License :: Other/Proprietary License
Classifier: Programming Language :: Python :: 3
Classifier: Programming Language :: Python :: 3.10
Classifier: Programming Language :: Python :: 3.11
Classifier: Programming Language :: Python :: 3.12
Classifier: Programming Language :: Python :: 3.13
Requires-Dist: beir (==2.0.0)
Requires-Dist: colbert-ai (>=0.2.20,<0.3.0)
Requires-Dist: fastembed (>=0.7.3,<0.8.0)
Requires-Dist: fastembed-gpu (>=0.7.3,<0.8.0)
Requires-Dist: qdrant-client (>=1.13.0,<2.0.0)
Requires-Dist: transformers (>=4.43.3,<4.45.0)
Project-URL: Repository, https://github.com/kacperlukawski/beir-qdrant
